{
  "align": "flex-start",
  "animateLoading": true,
  "backgroundColor": "#3A77DC",
  "backgroundColorActive": "#5D9AFF",
  "backgroundColorDisabled": "#C4D1F4",
  "backgroundColorHover": "#4987EE",
  "borderColor": "#3A77DC",
  "borderColorActive": "#3A77DC",
  "borderColorDisabled": "#C4D1F4",
  "borderColorHover": "#3A77DC",
  "bottomRow": 230,
  "buttonSize": "MEDIUM",
  "buttonVariant": "PRIMARY",
  "color": "#ffffff",
  "colorActive": "#ffffff",
  "colorDisabled": "#777B82",
  "colorHover": "#ffffff",
  "disabledWhenInvalid": false,
  "dynamicBindingPathList": [
    {
      "key": "isDisabled"
    }
  ],
  "dynamicPropertyPathList": [
    {
      "key": "onClick"
    },
    {
      "key": "isDisabled"
    }
  ],
  "dynamicTriggerPathList": [
    {
      "key": "onClick"
    }
  ],
  "iconAlign": "left",
  "iconSize": 16,
  "iconWeight": "regular",
  "isDefaultClickDisabled": true,
  "isDisabled": "{{\n!workgroupSelect.isValid || !roleSelect.isValid || !positionSelect.isValid || !managerSelect.isValid || !cooperationTypeSelect.isValid }}",
  "isLoading": false,
  "isVisible": true,
  "key": "pzww9ynf78",
  "leftColumn": 15,
  "minWidth": 120,
  "mobileBottomRow": 14,
  "mobileLeftColumn": 54,
  "mobileRightColumn": 60,
  "mobileTopRow": 10,
  "needsErrorInfo": false,
  "onClick": "{{init.handleSubmit()}}",
  "originalBottomRow": 230,
  "originalTopRow": 226,
  "parentColumnSpace": 4.5,
  "parentId": "e8yx99i2j0",
  "parentRowSpace": 10,
  "placement": "CENTER",
  "recaptchaType": "V3",
  "renderMode": "CANVAS",
  "resetFormOnClick": false,
  "responsiveBehavior": "hug",
  "rightColumn": 25,
  "text": "Зберегти",
  "tooltipPosition": "top",
  "topRow": 226,
  "type": "M4_BUTTON_WIDGET",
  "version": 1,
  "widgetId": "qn7blkyl0d",
  "widgetName": "Button5"
}