{
  "gitSyncId": "688f7c8487c169738493a99c_d82efabf-1e24-4518-8159-518a9a5d69ae",
  "id": "Attestation_Form_utils.onDecline",
  "pluginId": "js-plugin",
  "pluginType": "JS",
  "unpublishedAction": {
    "actionConfiguration": {
      "encodeParamsToggle": true,
      "jsArguments": [],
      "paginationType": "NONE",
      "timeoutInMillisecond": 10000
    },
    "collectionId": "Attestation_Form_utils",
    "confirmBeforeExecute": false,
    "datasource": {
      "isAutoGenerated": false,
      "name": "UNUSED_DATASOURCE",
      "pluginId": "js-plugin"
    },
    "dynamicBindingPathList": [
      {
        "key": "body"
      }
    ],
    "executeOnLoad": false,
    "fullyQualifiedName": "utils.onDecline",
    "name": "onDecline",
    "pageId": "Attestation_Form",
    "userSetOnLoad": false
  }
}