{
  "animateLoading": true,
  "bottomRow": 5,
  "dynamicBindingPathList": [],
  "dynamicHeight": "AUTO_HEIGHT",
  "dynamicTriggerPathList": [],
  "isLoading": false,
  "isVisible": true,
  "key": "ri0s7a1rhx",
  "leftColumn": 1,
  "maxDynamicHeight": 9000,
  "minDynamicHeight": 1,
  "minWidth": 450,
  "mobileBottomRow": 3,
  "mobileLeftColumn": 1,
  "mobileRightColumn": 9,
  "mobileTopRow": 1,
  "needsErrorInfo": false,
  "originalBottomRow": 9,
  "originalTopRow": 0,
  "overflow": "NONE",
  "parentColumnSpace": 20.515625,
  "parentId": "v7frod4ckg",
  "parentRowSpace": 10,
  "renderMode": "CANVAS",
  "responsiveBehavior": "fill",
  "rightColumn": 20,
  "shouldTruncate": false,
  "text": "Адаптація Працівника\n",
  "textAlign": "LEFT",
  "textColor": "#212121",
  "topRow": 0,
  "type": "M4_TEXT_WIDGET",
  "typography": "body3-b",
  "version": 1,
  "widgetId": "0mmc2mg4uc",
  "widgetName": "Text17Copy2"
}