{
  "animateLoading": true,
  "backgroundColor": "#ffffff",
  "backgroundColorActive": "#C4D1F4",
  "backgroundColorDisabled": "#ffffff",
  "backgroundColorHover": "#E3EEFF",
  "borderColor": "#3A77DC",
  "borderColorActive": "#3A77DC",
  "borderColorDisabled": "#B3B7BE",
  "borderColorHover": "#3A77DC",
  "borderRadius": "{{appsmith.theme.borderRadius.appBorderRadius}}",
  "bottomRow": 2,
  "boxShadow": "none",
  "buttonVariant": "OUTLINE",
  "color": "#3A77DC",
  "colorActive": "#3A77DC",
  "colorDisabled": "#B3B7BE",
  "colorHover": "#3A77DC",
  "configureMenuItems": {
    "config": {
      "id": "config",
      "isDisabled": false,
      "isVisible": true,
      "label": "{{MenuButton4.sourceData.map((currentItem, currentIndex) => ( currentItem.title))}}",
      "onClick": "{{utils.handleNavigate('Dismissal_Form', {selectedAssigmentId: currentItem.selectedAssigmentId})}}"
    },
    "id": "config",
    "label": "Configure menu items"
  },
  "dynamicBindingPathList": [
    {
      "key": "borderRadius"
    },
    {
      "key": "sourceData"
    },
    {
      "key": "isVisible"
    },
    {
      "key": "configureMenuItems.config.label"
    }
  ],
  "dynamicPropertyPathList": [
    {
      "key": "isVisible"
    },
    {
      "key": "configureMenuItems.config.onClick"
    }
  ],
  "dynamicTriggerPathList": [
    {
      "key": "configureMenuItems.config.onClick"
    }
  ],
  "iconAlign": "right",
  "iconName": "CaretDown",
  "iconSize": 24,
  "iconWeight": "regular",
  "isCompact": false,
  "isDisabled": false,
  "isLoading": false,
  "isVisible": "{{contentItems.dismissalItems.length > 0}}",
  "key": "atiqlbi6pn",
  "label": "Форма звільнення",
  "leftColumn": 50,
  "menuColor": "transparent",
  "menuItems": {
    "menuItem1": {
      "backgroundColor": "#ffffff",
      "backgroundColorActive": "#E3EEFF",
      "backgroundColorDisabled": "#F1F1F1",
      "backgroundColorHover": "#EEF4FF",
      "color": "#212121",
      "colorActive": "#212121",
      "colorDisabled": "#18181866",
      "colorHover": "#212121",
      "id": "menuItem1",
      "index": 0,
      "isDisabled": false,
      "isVisible": true,
      "label": "First Menu Item",
      "widgetId": ""
    },
    "menuItem2": {
      "backgroundColor": "#ffffff",
      "backgroundColorActive": "#E3EEFF",
      "backgroundColorDisabled": "#F1F1F1",
      "backgroundColorHover": "#EEF4FF",
      "color": "#212121",
      "colorActive": "#212121",
      "colorDisabled": "#18181866",
      "colorHover": "#212121",
      "id": "menuItem2",
      "index": 1,
      "isDisabled": false,
      "isVisible": true,
      "label": "Second Menu Item",
      "widgetId": ""
    },
    "menuItem3": {
      "backgroundColor": "#ffffff",
      "backgroundColorActive": "#E3EEFF",
      "backgroundColorDisabled": "#F1F1F1",
      "backgroundColorHover": "#EEF4FF",
      "color": "#212121",
      "colorActive": "#212121",
      "colorDisabled": "#18181866",
      "colorHover": "#212121",
      "id": "menuItem3",
      "index": 2,
      "isDisabled": false,
      "isVisible": true,
      "label": "Third Menu Item",
      "widgetId": ""
    }
  },
  "menuItemsSource": "DYNAMIC",
  "menuVariant": "PRIMARY",
  "mobileBottomRow": 2,
  "mobileLeftColumn": 50,
  "mobileRightColumn": 56,
  "mobileTopRow": 0,
  "needsErrorInfo": false,
  "parentColumnSpace": 10,
  "parentId": "kq519cwx2j",
  "parentRowSpace": 10,
  "placement": "CENTER",
  "renderMode": "CANVAS",
  "rightColumn": 56,
  "sourceData": "{{contentItems.dismissalItems}}",
  "topRow": 0,
  "type": "M4_MENU_BUTTON_WIDGET",
  "version": 1,
  "widgetId": "ly4nagsqxx",
  "widgetName": "MenuButton4"
}