{
  "accentColor": "{{appsmith.theme.colors.primaryColor}}",
  "animateLoading": true,
  "borderColor": "#c4d1f4",
  "borderRadius": "{{appsmith.theme.borderRadius.appBorderRadius}}",
  "bottomRow": 35,
  "boxShadow": "none",
  "defaultOptionValue": "",
  "dynamicBindingPathList": [
    {
      "key": "accentColor"
    },
    {
      "key": "borderRadius"
    },
    {
      "key": "labelText"
    },
    {
      "key": "placeholderText"
    },
    {
      "key": "sourceData"
    }
  ],
  "dynamicHeight": "FIXED",
  "dynamicPropertyPathList": [
    {
      "key": "sourceData"
    }
  ],
  "dynamicTriggerPathList": [
    {
      "key": "onOptionChange"
    }
  ],
  "errorMessage": "",
  "helperText": "",
  "isDisabled": false,
  "isFilterable": false,
  "isLoading": false,
  "isRequired": true,
  "isVisible": true,
  "key": "qp1yjudhlx",
  "labelAlignment": "left",
  "labelPosition": "Top",
  "labelText": "{{i18n.translate(\"dismissalReasonSelectLabel\")}}",
  "labelWidth": 5,
  "leftColumn": 1,
  "maxDynamicHeight": 9000,
  "minDynamicHeight": 4,
  "minWidth": 450,
  "mobileBottomRow": 36,
  "mobileLeftColumn": 37,
  "mobileRightColumn": 57,
  "mobileTopRow": 27,
  "needsErrorInfo": false,
  "onOptionChange": "",
  "optionLabel": "reason",
  "optionValue": "id",
  "originalBottomRow": 35,
  "originalTopRow": 28,
  "parentColumnSpace": 20.515625,
  "parentId": "847mhg4ux9",
  "parentRowSpace": 10,
  "placeholderText": "{{i18n.translate(\"dismissalReasonSelectPlaceholder\")}}",
  "renderMode": "CANVAS",
  "requiredMode": "required",
  "responsiveBehavior": "fill",
  "rightColumn": 32,
  "serverSideFiltering": false,
  "sourceData": "{{init.getReasons()}}",
  "topRow": 28,
  "type": "M4_SELECT_WIDGET",
  "version": 1,
  "widgetId": "k4d3pibdd6",
  "widgetName": "reasonInpt"
}