{
  "gitSyncId": "688f7c8487c169738493a99c_4470764e-0eb9-4036-993c-0b1975eb6f89",
  "id": "Add_User_get_person_by_fields",
  "pluginId": "graphql-plugin",
  "pluginType": "API",
  "unpublishedAction": {
    "actionConfiguration": {
      "autoGeneratedHeaders": [],
      "body": "query CheckIfPersonExists($name: String!, $familyName: String!, $birthday: date!) {\n  person: people_person_v0(where: {\n  \t_and: [\n       {Name: {_ilike: $name}},\n    \t {FamilyName: {_ilike: $familyName}},\n       {Birthday: {_eq: $birthday}}\n    ]\n  }) {\n    FestCloudID\n    Name\n    FamilyName\n    employee: person_festcloudid_employee {\n      PhotoLink\n      FestCloudID\n      assignment: assignment_employeefestcloudid_array {\n\t\t\t\tFestCloudID\n        EndDate\n        assignment_position: assignment_positionfestcloudid_position {\n          PositionName\n        }\n        assignment_ext: assignment_festcloudid_assignmentext {\n          Stage\n          FestCloudID\n        }\n      }\n    }\n    principal: person_festcloudid_principal {\n      contact: contact_principalfestcloudid_array(where: {_or: {EmailType: {_eq: \"Personal\"}, PhoneType: {_eq: \"Personal\"}}}) {\n        Email\n        PhoneNumber\n      }\n    }\n  }\n  affiliations:people_affiliation_v0(where: {\n  \t_and: [\n      {affiliation_assignmentfestcloudid_assignment: {\n      \tassignment_employeefestcloudid_employee: {\n        employee_festcloudid_person: {\n          Name: {_ilike: $name}, \n          FamilyName: {_ilike: $familyName}, \n          Birthday: {_eq: $birthday}\n        }\n      }\n    }}\n    ]\n  }) {\n    \tStatus\n    \tType\n  }\n}\n",
      "encodeParamsToggle": true,
      "formData": {
        "apiContentType": "application/json"
      },
      "headers": [
        {
          "key": "Authorization",
          "value": "Bearer {{appsmith.store.accessToken}}"
        },
        {
          "key": "X-Hasura-Role",
          "value": "{{SecurityService.getRoleByPermission(SecurityService.permissions.assignment_view)}}"
        }
      ],
      "httpMethod": "POST",
      "httpVersion": "HTTP11",
      "paginationType": "NONE",
      "path": "",
      "pluginSpecifiedTemplates": [
        {
          "value": true
        },
        {
          "value": "{\n\tname: {{nameInput.text}},\n\tfamilyName: {{familyNameInput.text}},\n\tbirthday: {{moment(datePicker.selectedDate).format('YYYY-MM-DD')}},\n}"
        },
        {
          "value": {}
        }
      ],
      "queryParameters": [],
      "timeoutInMillisecond": 60000
    },
    "confirmBeforeExecute": false,
    "datasource": {
      "datasourceConfiguration": {
        "url": "https://hasura-uat.srv.festcloud.ai/v1/graphql"
      },
      "isAutoGenerated": false,
      "name": "DEFAULT_REST_DATASOURCE",
      "pluginId": "graphql-plugin"
    },
    "dynamicBindingPathList": [
      {
        "key": "pluginSpecifiedTemplates[1].value"
      },
      {
        "key": "headers[1].value"
      }
    ],
    "executeOnLoad": false,
    "name": "get_person_by_fields",
    "pageId": "Add_User",
    "userSetOnLoad": true
  }
}