{
  "animateLoading": true,
  "bottomRow": 8,
  "dynamicBindingPathList": [],
  "dynamicHeight": "AUTO_HEIGHT",
  "dynamicTriggerPathList": [],
  "isLoading": false,
  "isVisible": true,
  "key": "2mufgmohg8",
  "leftColumn": 2,
  "maxDynamicHeight": 9000,
  "minDynamicHeight": 1,
  "minWidth": 450,
  "mobileBottomRow": 8,
  "mobileLeftColumn": 2,
  "mobileRightColumn": 10,
  "mobileTopRow": 6,
  "needsErrorInfo": false,
  "originalBottomRow": 8,
  "originalTopRow": 6,
  "overflow": "NONE",
  "parentColumnSpace": 6.9375,
  "parentId": "okhnaa50od",
  "parentRowSpace": 10,
  "renderMode": "CANVAS",
  "responsiveBehavior": "fill",
  "rightColumn": 57,
  "shouldTruncate": false,
  "text": "Працівник з такими даними вже є в системі",
  "textAlign": "LEFT",
  "textColor": "#777b82",
  "topRow": 6,
  "type": "M4_TEXT_WIDGET",
  "typography": "body5",
  "version": 1,
  "widgetId": "tu4quftnkn",
  "widgetName": "Text23"
}